airflow/providers/qlik_sense_nprinting/__init__.py
airflow/providers/qlik_sense_nprinting/hooks/__init__.py
airflow/providers/qlik_sense_nprinting/hooks/qlik_nprinting_hook_ntlm.py
airflow/providers/qlik_sense_nprinting/operators/__init__.py
airflow/providers/qlik_sense_nprinting/operators/reload_metadata_operator.py
airflow/providers/qlik_sense_nprinting/operators/reload_task_operator.py
airflow_provider_qlik_sense_nprinting-0.0.1.dist-info/LICENSE
airflow_provider_qlik_sense_nprinting-0.0.1.dist-info/METADATA
airflow_provider_qlik_sense_nprinting-0.0.1.dist-info/WHEEL
airflow_provider_qlik_sense_nprinting-0.0.1.dist-info/entry_points.txt
airflow_provider_qlik_sense_nprinting-0.0.1.dist-info/top_level.txt
airflow_provider_qlik_sense_nprinting-0.0.1.dist-info/RECORD
