Metadata-Version: 2.1
Name: airflow-provider-qlik-sense-nprinting
Version: 0.0.1
Summary: Airflow package provider to perform action into Qlik Sense NPrinting (reload apps, tasks ...).
Home-page: 
Author: Clement Parsy
Author-email: cparsy@decideom.fr
License: Apache License 2.0
Classifier: Framework :: Apache Airflow
Classifier: Framework :: Apache Airflow :: Provider
Requires-Python: ~=3.7
License-File: LICENSE
Requires-Dist: apache-airflow >=2.0
